colabgymrender/recorder.py
colabgymrender-1.0.9.dist-info/LICENSE.txt
colabgymrender-1.0.9.dist-info/METADATA
colabgymrender-1.0.9.dist-info/WHEEL
colabgymrender-1.0.9.dist-info/top_level.txt
colabgymrender-1.0.9.dist-info/RECORD
