Metadata-Version: 2.1
Name: colabgymrender
Version: 1.0.9
Summary: A wrapper for rendering OpenAI Gym environments in Google Colab
Home-page: https://github.com/Ryan-Rudes/colabgymrender
Author: Ryan Rudes
Author-email: ryanrudes@gmail.com
License: MIT
Download-URL: https://github.com/Ryan-Rudes/colabgymrender/archive/v1.0.9.tar.gz
Keywords: colab,gym,render,openai
Platform: UNKNOWN
Classifier: Development Status :: 5 - Production/Stable
Classifier: Intended Audience :: Developers
Classifier: Topic :: Software Development :: Build Tools
Classifier: License :: OSI Approved :: MIT License
Classifier: Programming Language :: Python :: 3
Classifier: Programming Language :: Python :: 3.4
Classifier: Programming Language :: Python :: 3.5
Classifier: Programming Language :: Python :: 3.6
Classifier: Programming Language :: Python :: 3.7
Classifier: Programming Language :: Python :: 3.8
Classifier: Programming Language :: Python :: 3.9
Classifier: Programming Language :: Python :: 3.10
License-File: LICENSE.txt
Requires-Dist: moviepy
